{
  "name": "replace_file_content",
  "args": {
    "AllowMultiple": "false",
    "Description": "\"Add vat_mention to setInvoiceData parameter to match state type definition\"",
    "EndLine": "371",
    "Instruction": "\"Add vat_mention property to setInvoiceData parameter\"",
    "ReplacementContent": "\"        setInvoiceData({\\n            invoice_number: `FAC-${Date.now().toString().slice(-6)}`,\\n            invoice_date: today,\\n            emitter: tenant?.legal_name || tenant?.name || \\\"Mon Club\\\",\\n            recipient: recipientStr,\\n            description: `${order.offer_name} (${order.offer_code})`,\\n            amount_ht: \\\"\\\",\\n            amount_ttc: (order.price_cents / 100).toFixed(2),\\n            notes: \\\"\\\",\\n            is_acquitted: true,\\n            vat_mention: tenant?.legal_vat_mention || \\\"\\\"\\n        });\"",
    "StartLine": "358",
    "TargetContent": "\"        setInvoiceData({\\n            invoice_number: `FAC-${Date.now().toString().slice(-6)}`,\\n            invoice_date: today,\\n            emitter: tenant?.legal_name || tenant?.name || \\\"Mon Club\\\",\\n            recipient: recipientStr,\\n            description: `${order.offer_name} (${order.offer_code})`,\\n            amount_ht: \\\"\\\",\\n            amount_ttc: (order.price_cents / 100).toFixed(2),\\n            notes: \\\"\\\",\\n            is_acquitted: true\\n        });\"",
    "TargetFile": "\"c:\\\\Users\\\\jdemo\\\\rezea-monorepo\\\\apps\\\\web\\\\src\\\\app\\\\[slug]\\\\admin\\\\shop\\\\orders\\\\page.tsx\"",
    "toolAction": "\"Adding vat_mention to setInvoiceData parameter\"",
    "toolSummary": "\"Replace file content in orders/page.tsx\""
  }
}