{
  "name": "replace_file_content",
  "args": {
    "AllowMultiple": "false",
    "Description": "\"Change marketing campaign card titles to font-semibold for a less prominent, cleaner look.\"",
    "EndLine": "1176",
    "Instruction": "\"Change font-bold to font-semibold in the marketing card h3 title.\"",
    "ReplacementContent": "\"                                                                 <h3 className=\\\"text-sm font-semibold text-slate-900 leading-snug group-hover:text-blue-600 transition-colors\\\">\"",
    "StartLine": "1170",
    "TargetContent": "\"                                                                 <h3 className=\\\"text-sm font-bold text-slate-900 leading-snug group-hover:text-blue-600 transition-colors\\\">\"",
    "TargetFile": "\"C:/Users/jdemo/rezea-monorepo/apps/web/src/app/[slug]/admin/emails/page.tsx\"",
    "toolAction": "\"Modifying font-weight of marketing card titles\"",
    "toolSummary": "\"Font weight modification\""
  }
}